flatten_single_item_arrays/__init__.py
flatten_single_item_arrays/cli.py
flatten_single_item_arrays-0.1.dist-info/LICENSE
flatten_single_item_arrays-0.1.dist-info/METADATA
flatten_single_item_arrays-0.1.dist-info/WHEEL
flatten_single_item_arrays-0.1.dist-info/entry_points.txt
flatten_single_item_arrays-0.1.dist-info/top_level.txt
flatten_single_item_arrays-0.1.dist-info/RECORD
