Metadata-Version: 2.1
Name: flatten-single-item-arrays
Version: 0.1
Summary: Given a JSON list of objects, flatten any keys which always contain single item arrays to just a single value
Home-page: https://github.com/simonw/flatten-single-item-arrays
Author: Simon Willison
License: Apache License, Version 2.0
Project-URL: Issues, https://github.com/simonw/flatten-single-item-arrays/issues
Project-URL: CI, https://github.com/simonw/flatten-single-item-arrays/actions
Project-URL: Changelog, https://github.com/simonw/flatten-single-item-arrays/releases
Platform: UNKNOWN
Requires-Python: >=3.6
Requires-Dist: click
Provides-Extra: test
Requires-Dist: pytest ; extra == 'test'
